{"100": 1, "있습니다": 2, "자주": 2, "안뿌리게": 1, "되서": 1, "사용하진": 1, "못했네요": 1, "쓰는게": 1, "귀찮": 1, "고": 1, "사용하고": 1, "있어요": 1, "분홍색": 1, "해야할": 1, "손에": 1, "7번": 1, "펌핑해서": 1, "얼굴에": 1, "발라주고": 1, "뿌리기엔": 1, "안좋은데": 1, "별로인": 1, "같아용": 1, "다": 1, "쓰게": 1, "되네용": 1, "수시로": 1, "뿌렸습니다": 1, "워터가": 1, "나눠져있어서": 1, "흔들어": 1, "써야함": 1, "썽": 1, "안쓰고": 1, "바디미스트로": 1, "쓸거양": 1, "하나만": 1, "바르기에는": 1, "부족함이": 1, "편입니다": 1, "흡수되고": 1, "안개분사정도로": 1, "개선되면": 1, "좋을": 1, "거": 1, "층이라": 1, "쓸": 1, "때마다": 1, "섞어써야": 1, "하는": 1, "번거로움이": 1, "있긴": 1, "외출해서": 1, "사용하기에는": 1, "답답한": 1, "습해지고": 1, "더워지면": 1, "사용하기": 1, "힘들": 1, "같다는": 1, "생각이": 1, "드네요": 1, "안가게되네요": 1}