{"대용으로": 4, "사용합니다": 1, "일반": 1, "미스트로": 4, "쓰기는": 1, "영양성분이": 1, "사용": 1, "중입니다": 1, "분사도": 1, "골고루": 2, "잘되고": 1, "좋습니다": 4, "좋으나": 1, "수시로": 13, "뿌려주고": 7, "있어요": 13, "나서": 2, "쓰면": 1, "딱이에뇨": 1, "뿌리기에도": 2, "칙칙": 4, "뿌려주면": 8, "정말": 3, "좋아서": 1, "뿌리면": 3, "금방": 1, "써요": 1, "흔들고": 1, "뿌리는거라": 1, "편해요": 3, "마구마구": 1, "뿌려서": 3, "쓰십니다": 1, "쓰고": 3, "건조할": 2, "때도": 2, "뿌리고": 7, "화장할": 1, "뿌려요": 6, "스킨처럼": 1, "쓰기도": 3, "좋고": 8, "메이크업": 1, "마지막": 1, "단계에": 1, "마무리": 1, "해주면": 1, "좋아요": 19, "사용하기도": 1, "편하고": 2, "건조할때": 3, "항시": 1, "두고": 4, "샤워": 1, "후에": 1, "사용하는": 3, "제품이에요": 1, "갖다놓고": 1, "씻고": 1, "나와요": 1, "막": 3, "쓰기": 3, "좋은거": 1, "내내": 3, "사용하고": 9, "전": 2, "괜찮아요": 1, "복합성피부에": 1, "얼굴에": 5, "간편하고": 1, "좋은것": 2, "요즘엔": 2, "뿌리기만": 2, "하면": 2, "되닌깐": 1, "있답니다": 3, "안개미스트": 1, "같은": 1, "딱이랍니다": 2, "다양한": 1, "용량이": 1, "있지만": 1, "묻어서": 1, "갠적": 1, "기능성": 1, "화장품": 1, "비건": 1, "좋을것": 2, "달바는": 1, "수분과": 1, "영양": 1, "보충하기에": 1, "좋은": 6, "좋더라고요": 1, "겨울엔": 1, "흔들어서": 2, "여름에는": 1, "됐답니다": 1, "4계절": 2, "분사되어서": 1, "맘에": 2, "든답니다": 1, "세럼을": 1, "스프레이하는": 1, "사정": 1, "없이": 1, "뿌려준답니다": 1, "항상": 2, "너무편하고": 1, "좋답니다": 1, "손에도": 1, "묻지도": 1, "않고": 2, "뿌려줌": 1, "얼굴": 3, "당김도": 1, "발라주면": 1, "짱이랍니다": 1, "순딩순딩하면서": 1, "점심시간": 1, "지나서": 1, "건조하다고": 2, "느낄": 1, "담에도": 1, "먼저": 1, "얼굴이": 1, "책상에": 1, "놓고": 1, "중간중간": 1, "뿌려주기": 1, "목에": 1, "발라주고": 1, "가지고": 2, "다나면서": 1, "뿌리기": 6, "딱자마자": 1, "뿌려": 4, "주는": 2, "용도로": 2, "틈틈이": 1, "줘요": 1, "주면": 1, "편리하고": 1, "사용할수": 1, "있구여": 1, "여름에": 1, "바디로션": 1, "대신": 2, "사용중이에요": 1, "흔들어주고": 1, "뿌려주니": 3, "피부에": 3, "좋을거": 1, "같단": 1, "생각에": 1, "사용하니": 1, "뿌려주기만": 1, "되니까": 1, "간편해서": 1, "자주": 4, "손이가요": 1, "곳에서": 1, "편하게": 2, "구입할": 1, "좋네요": 2, "전후로": 2, "가볍게": 1, "발라주기에": 1, "틈틈히": 1, "조아요": 2, "마다": 2, "뿌리기도": 3, "하는데": 1, "좋운거": 1, "보통": 1, "집에서나": 1, "밤에": 1, "스킨케어": 1, "마지막에": 1, "뿌리는게": 1, "입원할때": 1, "간단한": 1, "화장품으로": 1, "챙겨왔는데": 1, "딱이에요": 1, "손닿는곳에서": 1, "쉽게": 1, "두면": 1, "언제든": 1, "조금씩": 1, "차에두고": 1, "뿌리는데": 1, "조아영": 1, "충분히": 1, "바르고": 1, "건조한데": 1, "아주": 6, "샤워하고": 1, "나올": 1, "뿌려줬는데": 1, "분사가": 1, "됩니다": 1, "상관없이": 2, "좋음을": 1, "느껴서": 1, "저도": 1, "뿌듯합니다": 1, "할": 2, "쓸": 1, "있는": 1, "점이": 1, "강점이에요": 1, "발라서": 2, "휴대용으로": 1, "들고다니기에": 1, "뿌리기에": 1, "행사하네요": 1, "중간에": 1, "수정": 1, "활용": 1, "가능": 1, "메이크업이나": 1, "선크림": 1, "기초": 1, "레이어링": 1, "할때도": 1, "활용할수": 1, "사용가능": 1, "고루고루": 1, "퍼펙트": 1, "필수템": 1, "있고": 2, "사용한답니다": 1, "세안직후": 1, "사용하기": 1, "계절에": 1, "수정화장할": 1, "사용해도": 1, "쓰기에": 1, "뿌려주는": 2, "구매했는데": 1, "사용하는걸요": 1, "아이템입니다": 1, "사용하기좋아요": 1, "만족스러운": 1, "제품입니다": 2, "겸": 1, "뿌려주곤": 2, "하는데요": 1, "후다닥": 1, "좋아용": 3, "전에도": 1, "주기": 1, "미스트인것": 1, "같습니다": 3, "미스트처럼": 1, "사용하는데": 1, "때마다": 2, "발라주기": 1, "하면되니까": 1, "편리해서": 1, "좋은데": 1, "아니고": 1, "미스트니": 1, "안심하고": 1, "헤어제품": 1, "뿌리게": 1, "겨울에": 1, "대신에": 1, "땡기려고": 1, "마구": 1, "줍니다": 1, "사용하기좋은가요": 1, "스킨대용으로": 1, "사용하고있어요": 1, "후로": 1, "사무실에서도": 1, "사용하려고": 1, "써도": 2, "되고": 2, "휘뚜루마뚜루입니당": 1, "하고": 2, "난": 1, "뒤에": 1, "쓰는게": 1, "사무실에서": 2, "세럼은": 1, "필수인듯": 1, "회사에": 1, "나와서": 2, "얼굴여": 1, "뿌려줘요": 1, "뿌려줍니다": 1, "뿌려용": 1, "느낄때마다": 1, "외출할때": 1, "마음에": 1, "들어서": 1, "뿌리니": 2, "탈": 1, "후": 1, "욕실에": 1, "바로바로": 2, "사용하면": 1, "사용가능해요": 1, "쓰시고": 1, "사용하십니다": 1, "바디미스트루": 1, "써두": 1, "집에서": 1, "씩씩": 1, "필수템입니다": 2, "달바를": 1, "좋아여": 1, "가방속에": 1, "넣어다니며": 1, "사용해요": 1, "언제나": 1, "쓸수": 1, "좋은데요": 1, "위에": 1, "뿌려도": 1, "괜찮더라구요": 1, "느껴질때": 1, "건조해지기전": 1, "좋은제품이에요": 1, "종종": 2, "뿌리구요": 1, "외출시": 1, "실내": 1, "사무실이나": 1, "도서관에서": 1, "씁니다": 2, "집에도두고": 1, "굿굿": 1, "섞은후": 1, "방식인데": 1, "분사력": 1, "만족하고요": 1, "분사": 1, "넘": 1, "들어요": 1, "회사에도": 1, "구매하고": 1, "중이에요": 1, "어렵지": 1, "특히": 1, "환절기때": 1, "유용하게": 1, "근데": 1, "오후에": 1, "건조했을때": 1, "목욕하고": 1, "나왔을때": 1, "수정화장전에도": 1, "쓰윽": 1, "수정하고": 1, "활용도가": 1, "높아": 1, "이곳저곳": 1, "뿌리다": 1, "보니": 1, "확확": 1, "많네요": 1, "화장대에": 1, "하나씩두고": 1, "고르게": 2, "뿌려줘서인지": 2, "스킨케어하기에": 2, "제품인것": 2, "레이어링을": 1, "해도": 1, "생활템임": 1, "기본템중에": 1, "하나입니다": 1}