{"제일": 1, "향이야": 1, "화장후에": 1, "모공넓은곳은": 1, "막": 2, "이제품은": 1, "복합성이나": 1, "지성인": 3, "향이": 18, "분사할때": 1, "개인적인": 2, "향은": 4, "여드룸": 1, "가끔": 3, "냄새가": 1, "수부지": 1, "손에만": 1, "피부": 5, "화장품": 1, "트러블이": 2, "뿌리면": 2, "뿌리자": 1, "볼쪽에": 1, "코가": 1, "지성": 2, "여름에는": 1, "건성에겐": 1, "건성": 1, "수부지민감인": 1, "속은": 1, "정말": 1, "전": 1, "향": 2, "눈에": 4, "지성피부가": 1, "인공적인": 1, "젊은분들": 1, "눈이": 2, "민감성": 1, "지성이쓰면": 1, "엄마는": 1, "트러블": 1, "안맞으시는": 1, "피부나": 1, "이거만": 1, "지성인들은": 1, "수분부족지성이라": 1, "손에남는": 1, "지성피부의": 1, "20대": 1, "여드름": 1, "특유의": 2, "건성이라": 2, "지성이": 1, "눈에도": 1, "복합성인": 1, "비추이지만": 1, "건성분들은": 1, "피부들에겐": 1, "요즘": 1, "뿌리고": 1, "자극이": 1, "지성분들께는": 1, "눈": 1, "복합성": 1, "안돼요": 1, "건성분들": 1, "민감성피부한테는": 1, "민감성피부에는": 1, "두눈": 1, "얼굴에": 1, "건성이던": 1, "베이스": 1, "복합성이라": 1}