{"약하지만": 1, "속땡김이": 1, "있었어요": 1, "전혀": 1, "촉촉하지": 1, "않았어요": 1, "날아가버리는": 1, "부족은": 1, "당연하고": 1, "개선도": 1, "안되는것": 1, "같고": 1, "극건성피부라": 1, "분사되지는않습니다": 1, "별로에요": 1, "건조해지고": 1, "위해": 1, "굳이": 1, "필요한": 1, "같지는": 1, "않아요": 3, "착": 1, "붙으면": 1, "좋겠는데": 1, "그렇지않고": 1, "촉촉하진": 2, "않은": 1, "때는": 1, "건조한": 2, "들어요": 1, "피부가": 3, "좋아졌다거나": 1, "진정된다는": 1, "아니고": 1, "효과가": 1, "있나": 1, "싶었는데": 1, "대용으로": 1, "쓰기에는": 1, "촉촉함이": 2, "부족한": 1, "촉촉하다는": 1, "덜한게": 1, "아쉽더라구요": 1, "절실한": 1, "템": 1, "피부에": 1, "드라마틱하게": 1, "효과있는건": 1, "아닌데": 1, "탄탄히": 1, "쌓아놓고": 1, "미스트를": 1, "뿌려도": 1, "수분을": 2, "뺏기는": 1, "느낌이고": 1, "겨울철엔": 1, "더더욱": 1, "채워주지": 1, "그리": 1, "좋지": 1, "않음": 1, "원하는": 1, "않았던": 1, "것보다": 1, "덜": 1, "느껴지더라구요": 1, "금방": 2, "수분감이": 1, "날아가긴": 1, "분들에게": 1, "피부엔": 1, "맞나봐요": 1, "촉촉하지는": 1, "않지만": 2, "건조할": 1, "기초를": 1, "싶어": 1, "뿌리면": 2, "당기는": 1, "느낌이더라구요": 1, "그치만": 1, "뿌리고": 1, "유분감이": 2, "느껴져요": 1, "그래도": 1, "돌려줘요": 1, "잡아주진": 1, "못했어요": 1, "꽝": 1, "있지만": 2, "해결이": 1, "안되요": 1, "모르겠어서": 2, "나진": 1, "뿌려줘야": 1, "보습감이": 2, "이정도로": 1, "약한줄": 1, "제품덕에": 1, "알았네요": 1, "효과도": 1, "모르겠고": 1, "당기고": 1, "당김이": 1, "심하긴해영": 1, "아쉬워요": 1, "건조해": 1, "지는": 1, "편이에요": 1, "날라가서": 1, "같진": 1, "떨어지거나": 1, "들어서": 1, "안맞는거": 1, "넘": 1, "많긴": 1, "함": 1, "크게": 1, "효과": 1, "보는": 1, "제품이": 1, "아니지만": 1, "분사력이": 1, "불만족": 1, "스러웠는데": 1, "리뉴얼": 1, "오래가지는": 1, "않는다는": 1, "아쉬움은": 1, "어쩔수": 1, "없습니다": 1, "메이크업": 1, "후에": 1, "뭔가": 1, "건조해져요": 1, "하나도": 1, "없음": 1, "끈적거린다고": 1, "느낄": 1, "수도": 1, "있어요": 1, "뿌리기": 1, "오일리": 1, "할": 1, "된다는": 1, "없고": 1, "빨리": 1, "날라가는": 1, "들었어요": 1}