{"메이크업": 16, "고르게": 32, "미세하게": 5, "세수하자마자": 5, "사용하기가": 1, "세안": 51, "건조할": 28, "가지고": 12, "분사력이": 84, "자주": 23, "이것만": 2, "안개분사": 17, "화장할때": 12, "분사력도": 224, "다용도로": 4, "들고": 9, "건조할틈": 1, "요즘같은": 6, "샤워하고": 36, "수분과": 1, "진정이": 3, "작은": 8, "매일": 28, "온천수": 1, "스킨팩으로도": 2, "뿌려서": 1, "메이크업할때": 2, "거실에도": 1, "써도": 1, "되지만": 1, "주로": 4, "회사에서": 3, "기초할": 1, "겨울이라": 1, "건조할때마다": 24, "수시로": 103, "휘뚜루마뚜루": 6, "세안하고": 35, "건조하다고": 2, "데일리": 6, "스킨": 34, "데일리로": 26, "분사력": 59, "스킨대용으로나": 1, "일어나자마자": 1, "무난하게": 50, "사계절": 12, "막": 28, "건조": 2, "겨울철": 2, "화장전": 4, "겨울철에도": 1, "여름에도": 1, "사용하기": 18, "미스트를": 6, "샤워후": 7, "상황에": 1, "얼굴에": 60, "무조건": 2, "집에서": 25, "안개처럼분사대기도하구": 1, "분사량도": 1, "화장하기": 11, "여러가지": 1, "건조할때": 19, "분사력은": 44, "화장할때마다": 1, "무난하": 1, "스킨대": 1, "얼굴이며": 2, "오래": 1, "분사할": 1, "사무실에서": 13, "욕실": 3, "두루두루": 4, "나갈": 1, "케어": 1, "활용하기에도": 1, "피부가": 7, "고루": 6, "분사": 3, "걍": 3, "한번에": 2, "가볍게": 78, "클렌징이랑": 1, "수분충전을": 1, "두개라서": 1, "분사력도좋고": 1, "화장솜에": 19, "편함": 1, "뿌려지는": 2, "넣어둘": 1, "편허게": 1, "매일매일": 15, "토너대용으로": 1, "꼭": 3, "구비해둬야": 1, "물": 2, "적실": 1, "얼굴": 32, "데일리하게": 2, "분사가": 15, "안개분사형이라": 7, "마뚜루": 2, "좋은가요": 1, "스킨케어": 26, "바디": 1, "뿌려줘도": 1, "부담없어요": 1, "뿌려줘도좋아요": 1, "사용하면": 1, "가볍게수분을": 1, "곳곳": 1, "사용해도": 3, "찾고계시는분들": 1, "무난템으로": 1, "좋은편인데": 1, "몸에": 13, "아주": 7, "분사력까지": 1, "여름에는": 8, "안개분사라": 25, "들고다니면서": 8, "화장솜은": 1, "건조한": 15, "닦아내는": 1, "제품인데": 1, "세안이나": 1, "푸석푸석할때": 1, "사무실에": 11, "화장": 29, "위에": 1, "수분팩할때": 1, "욕실에": 12, "건조함과": 1, "저녁에": 2, "아무때나": 21, "분사도": 35, "요즘": 8, "쿠션하기전에": 1, "바디에도": 6, "안개분사로": 18, "자주자주": 8, "50는": 3, "처음엔": 2, "곳에나": 1, "계절": 11, "몇번을": 1, "온가족이": 5, "사용": 5, "열이": 1, "여행갈때": 3, "퍼프에": 19, "피부화장": 4, "피부이신": 1, "차에": 1, "마스크": 5, "휴대용으로": 15, "뿌려주기에": 1, "사무실": 6, "지금처럼": 2, "휴대용이나": 1, "스킨케어전에": 1, "화장전에": 5, "세안직후": 2, "등에도": 2, "샤워하면서": 2, "로션이": 1, "화장대에": 4, "씻고": 25, "마스크팩처럼": 1, "얼굴이랑": 1, "바디오일": 1, "분사되는": 2, "안개": 9, "뿌려주거나": 1, "사용중입니다": 1, "안개분사라서": 19, "얼굴뿐이": 1, "머리": 3, "파데": 3, "언제나": 4, "지금도": 1, "올": 2, "날씨가": 2, "겨울엔": 2, "쿠션에": 3, "건조하다": 3, "샤워나": 3, "1번세럼": 1, "여드름": 1, "냉장고에": 6, "여름엔": 3, "여름": 3, "편해요": 1, "왠만한": 1, "토너": 26, "뛰어나서": 1, "귀찮은": 1, "세수": 8, "여기저기": 7, "간단하게": 5, "할때도": 1, "자기전이나": 1, "주기적으로": 2, "요즘처럼": 3, "문안하게": 2, "졸릴": 1, "세수하고": 47, "세수바로": 1, "스킨케어할때": 2, "세안후": 12, "피부에": 6, "일하다": 1, "스킨전에": 1, "화장할때도": 2, "쓰기": 13, "샤워하거나": 3, "분사력은좋아요": 1, "다사용해도좋을거": 1, "좋을거같아요": 1, "세안하자마자": 4, "세안후에": 5, "대용으로": 3, "되니": 1, "세럼": 1, "피부": 12, "한번씩": 3, "바르기": 6, "아무렇게": 1, "중간중간에": 1, "학교사물함에": 1, "스킨케어도": 2, "겨울에는": 7, "닦토나": 1, "메이크업하기": 1, "부담없이": 18, "수영장갈때": 1, "사무실엣에도": 1, "거실에": 2, "가방에": 12, "뭐할때나": 1, "온": 11, "솜에": 3, "작은거라": 1, "여러번": 6, "닦토": 1, "토너팩으로도": 1, "욕실에두고": 3, "아낌없이": 1, "샤워후에": 4, "직후": 1, "하나는": 17, "나머지": 1, "여름철": 3, "화장하기전": 1, "분사되는점이": 1, "바디스프레이로": 1, "화장하고": 5, "두개": 2, "잠깐잠깐": 1, "분사력음": 1, "골고루": 17, "세수하고서": 1, "회사에": 3, "분사력좋고": 3, "픽서로": 1, "굉장히": 4, "대용양이라": 1, "아침에": 7, "피부타입": 5, "기초": 6, "간편하게": 16, "세수하고나서": 2, "좋음": 1, "집에": 15, "가장": 4, "안개분사되어": 1, "깔끔해서화장": 1, "에센스로선": 1, "책상에": 3, "365일": 3, "스킨팩을": 1, "스킨으로": 5, "팩으로도": 2, "4계절": 4, "미스트도": 1, "언제든": 3, "샤워": 23, "거꾸로": 2, "등이나": 2, "팩하듯이": 1, "아침저녁으로": 2, "학생때부터": 1, "하장실에서": 1, "학교에서": 2, "큰": 3, "분사는": 6, "들고다미면서": 1, "얼굴이": 6, "일상생활하면서": 1, "휴대하기도": 5, "집에두고": 2, "적셔주는": 1, "한번": 7, "갖고": 1, "안개분사가": 3, "들고다니기도": 1, "또는": 1, "멀티로": 1, "여행영으로": 1, "여름에": 13, "스킨처럼": 1, "무난히": 4, "스킨대용으로": 20, "건조한날": 1, "건조에": 1, "뿌리기는": 1, "휴대도": 2, "가방에도": 1, "막뿌리기": 3, "편리하기까지": 1, "간편해요": 1, "학교": 1, "파운데이션": 7, "가끔": 8, "휴대용이": 1, "수분을": 3, "안개분사는": 1, "비행기에": 1, "안개분사여서": 10, "모든": 2, "스킨대신": 20, "되게": 1, "화장하기전에": 2, "세수나": 1, "내가": 1, "스킨대용으로도": 1, "두고": 5, "미스트뿌리고": 1, "미세한": 2, "회장솜에": 1, "올영에서도": 1, "바디로션": 6, "안개분사를": 1, "이후": 1, "기초제품을": 1, "휘뚤마뚤": 1, "헤어": 1, "열": 2, "스킨팩": 4, "아무렇게나": 1, "미스트로": 6, "쓰기도": 2, "파데랑": 1, "낭비없이": 1, "편하게": 9, "가까이": 1, "샤워실에": 2, "샤워하고도": 1, "화장할": 17, "샤워한": 2, "몸에도": 7, "여행갈": 3, "신랑이": 1, "뿌려줍니다": 1, "분사하는것만": 1, "여름내내": 2, "사용해요": 2, "가지고다니면서": 1, "순해서": 1, "문안히": 1, "전혀": 1, "이걸로": 1, "화장실에": 11, "마스크팩": 1, "계속": 3, "여행": 8, "계절에": 1, "가을이라": 1, "건도할": 1, "직장에서": 1, "사계벌": 1, "아벤느미스트사용해주고": 1, "팍팍": 1, "스킨팩처럼": 1, "목": 1, "균일하게": 1, "평상시에": 3, "여러까지": 1, "안개분사되서": 1, "무난무난하게": 6, "온가족이사용함": 1, "들고다니기편하고": 1, "평소에도": 2, "항상": 13, "뿌리기좋아요": 1, "뿌렸을때": 1, "밖에서": 2, "바디와": 1, "미스트중에서": 1, "제가": 1, "아침이나": 2, "아주아주": 1, "아침에는": 2, "수분이": 2, "휴대용은": 1, "세수하거나": 3, "휴대하기": 11, "세안하고나서": 1, "가볍고": 1, "히터를": 1, "시간이": 2, "스펀지를": 2, "특히": 4, "요즘같이": 4, "사용중이에요": 1, "있다가": 1, "커서": 1, "집이나": 3, "안개분사식이라": 2, "딱히": 1, "전신에": 2, "파데나": 2, "초반에는": 1, "수분필요할때쓰려고요": 1, "체육관에서": 1, "피부진정시킬때나": 1, "자기전에": 3, "아무나": 1, "로션": 5, "편리해서": 1, "얼굴뿐만": 4, "온가족같이": 1, "안개분사형태로": 1, "집에만": 1, "더워지니": 1, "씻고나서": 5, "사용하기에": 1, "실내에서": 3, "평소에": 3, "가족들이": 1, "샤워직후": 1, "리프레쉬할": 1, "미스트지만": 1, "손쉽게": 1, "간편하고": 2, "가벼운": 4, "미세분사지만": 1, "티존부위나": 1, "들고다니기는": 1, "부담": 6, "좋고": 5, "수정": 4, "세안후나": 1, "자주쓰는": 1, "닥토로": 1, "덜어": 1, "차": 1, "팩으로": 3, "여름이라": 1, "해외": 1, "자주에용": 1, "퍼프를": 1, "아벤느가": 2, "휴대하기에도": 4, "300와": 1, "클렌징": 3, "겨울에": 3, "구매했어요": 1, "온가족용": 1, "닦는토너": 1, "환절기엔": 1, "얇은": 1, "거부감없이": 1, "틈만나면": 2, "미스트랑": 2, "민감하신": 2, "크림을": 3, "뿌리는": 3, "에센스랑": 1, "온몸에": 2, "넓은": 1, "안개처럼": 9, "작아서": 1, "휴대성도": 4, "점심먹고": 1, "뿌리면": 2, "알뜰하게": 1, "누구나": 2, "아무곳에": 1, "건조하거나": 3, "제품": 1, "지금은": 1, "나갈때": 1, "작은걸로": 1, "곱게": 1, "들고다니기": 3, "메이크업때도": 1, "뿌려": 3, "닥토처럼": 1, "기초전": 1, "사용하기도": 5, "쓰면좋아요": 1, "조금만": 2, "기내에": 1, "두피에도": 1, "안개분사까지는": 2, "운동하고": 1, "넘": 1, "뿌리기": 7, "편하고": 2, "가족": 3, "짱": 2, "가볍게뿌리기": 1, "스킨대신으로": 2, "일상생활에서": 1, "무난하니": 1, "건조할때나": 3, "얼굴아니라도": 1, "화정전에": 1, "조절하면서": 1, "저같이": 1, "손에": 4, "화장대": 2, "화장하면서": 1, "스펀지에": 1, "샤워하고나서": 1, "무난": 1, "막쓰기": 4, "얼굴에도": 5, "얼굴과": 3, "귀찮을": 1, "미세분사로": 1, "뿌리기만하면되니": 1, "팩하기도": 1, "햇빛": 1, "닦토용으로": 1, "기본무난템이라": 1, "냉장고에넣어쓰니": 1, "데일리에": 1, "더블제품이라": 1, "분사형": 1, "이라": 1, "아무떼나": 1, "분사되서": 1, "분사해서": 1, "휴대용도": 2, "화장후에": 2, "안개분사랑": 1, "당길때": 1, "머리말리고": 1, "머리드라이": 1, "스켄케어": 1, "순으로": 1, "잘만": 2, "때마다": 3, "메이크업시에": 2, "안개분사처럼": 1, "수분감": 1, "아무생각없이": 1, "분사력도좋네요": 1, "전체에": 1, "큰거는": 1, "작은거는": 4, "씻고나와서": 4, "화장이나": 1, "300인데": 1, "밤": 1, "겁나": 1, "얼굴뿐만아니라": 1, "휴대용으호": 1, "피부타입에": 2, "미스트면": 1, "화장전이나": 2, "피부과갔다": 1, "사무실에도": 2, "메아크업": 1, "수분": 2, "여러군데": 1, "새안하고": 1, "봄": 1, "부드럽게": 6, "등드름": 3, "솜적셔서": 1, "휴대하기가": 3, "분사형이라서": 1, "대충": 2, "찍": 1, "아무데나": 1, "퍼프애도": 1, "토너패드": 1, "라포제보다": 1, "편리하게": 2, "열오를때": 1, "바르지": 1, "회사": 1, "매우": 2, "리들샷": 1, "마구마구": 3, "기분": 1, "몸이나": 2, "가스스프레이": 1, "수정화장용으로": 1, "여름철에": 1, "우수해요": 1, "베이스": 2, "여기저기서": 1, "사용합니다": 1, "무난해서": 1, "매일사용하는": 1, "큰용량은": 1, "작은용량은": 2, "물기": 2, "안에": 1, "메이크업하면서": 1, "사볍게": 1, "무난하고도": 1, "누르는대로": 1, "바디에": 2, "무한대로": 1, "분사범위가": 1, "용량": 2, "사서도": 2, "아무곳에나": 1, "넓게": 1, "나서": 1, "파운데이션이나": 2, "욕실에서": 1, "누르고": 2, "화장대로": 1, "세수하기": 2, "바르기에": 1, "쓸수있고": 1, "등산하거나": 1, "좋은데": 2, "1주에": 1, "계절과": 1, "스킨로션": 1, "얇고": 1, "화장위에": 2, "쓰긴": 1, "빨갛던": 1, "300가": 1, "빠르고": 3, "온가족템": 1, "기존에": 1, "팩이나": 1, "중2딸아이": 1, "안개미스트처럼": 1, "마사지": 1, "필요할때도": 1, "미니": 2, "로션바르기전에": 1, "시시때때로": 1, "상": 1, "여행용이나": 2, "간편상": 1, "휴대성이": 2, "좋은": 2, "부담없이쓰기좋은": 1, "집": 4, "촉촉하게": 1, "막쓰기에도좋고": 1, "등에": 1, "얼굴스킨": 1, "켜있을때도": 1, "뿌려주기": 3, "온천수로": 1, "휴대하기좋아서": 1, "예민할": 2, "사용이": 2, "저희집": 1, "퍽퍽쓰기": 1, "작은사이즈로": 1, "언제든지": 4, "화장실": 2, "바디미스트": 2, "바디미스트로": 3, "올여름": 1, "대부분": 1, "팩못한날에는": 1, "여러곳": 1, "가게에서": 1, "금방": 1, "닥토": 2, "오일": 1, "씻고난뒤": 1, "늘": 1, "틈틈이": 1, "필요할": 1, "여행용으로": 2, "뿌리고": 2, "로션바르기전후로": 1, "선크린바르고나서도": 1, "내내": 1, "쓰는": 1, "부위": 1, "뿐": 2, "휘뚜루마뚜루로": 1, "용량은": 1, "기내용이나": 1, "얼굴뿐": 1, "휴대와": 1, "자주뿌리기": 1, "겨울철에": 1, "한": 4, "쓰기엔": 1, "씻고나올때마다": 1, "예민하고": 1, "얼굴말고": 1, "세수직후": 1, "화장하면서도": 1, "요거": 1, "무난하게쓰기좋아요": 1, "안개분사에": 2, "사이즈": 1, "미니사이즈는": 1, "제일": 1, "얼굴부터": 1, "작은입자가": 1, "휴대용으로도": 4, "세수하고나면": 1, "씻자마자": 3, "아이들도": 1, "스킨대신쓰기도": 1, "지금같이": 1, "좋아서": 3, "가까이서": 1, "친구도": 1, "뿌려지고": 1, "손이": 2, "할수": 2, "뿌려져요": 2, "쓰기좋을거": 2, "레이어링": 1, "작은건": 3, "쓸": 1, "아이부터": 1, "자극": 2, "들고가면": 1, "책상위에": 1, "토너처럼": 1, "세수하러": 1, "스킨때신": 1, "스킨이나": 1, "직장": 1, "분사력으로": 1, "많이들": 1, "선크림": 2, "두": 1, "팩토할때": 1, "아침저녁": 1, "들지만무난하게": 1, "사용할": 3, "퍼프": 1, "달아오를때": 1, "좋네요": 1, "필링기": 1, "수정화장": 1, "공부하다가": 2, "화장할때에도": 1, "에프킬라": 1, "건조함": 1, "스킨대용보다는": 1, "즉각적으로": 1, "가을이나": 1, "일하면서도": 1, "로션이나": 1, "화장을": 1, "사실": 1, "아이몸에두": 1, "일년": 1, "사시사철": 1, "집안": 1, "정말": 4, "화장위에도": 1, "저는둘다중간에서": 1, "안개분사되고": 1, "종종": 1, "환절기랑": 1, "겨울철에는": 1, "가능한": 1, "피부타입을": 1, "두루두루사용하기에": 1, "좋아용": 1, "이거는": 2, "여행갈때나": 2, "들고다니기에도": 1, "귀찮으면": 1, "앞머리에": 1, "틈틈히": 2, "확실히": 2, "건조한곳": 1, "막사용하기": 1, "대용랑으로": 1, "여름이고": 1, "할일": 1, "두번": 1, "화장실이랑": 1, "2번": 1, "저의": 1, "사이즈에": 1, "간격으로": 1, "바르고": 1, "여러모로": 3, "붉어짐": 1, "아니라": 4, "얕고": 1, "겨울에도": 2, "잘되요": 1, "넣어도": 1, "사용하고": 1, "평소": 3, "기초는": 1, "크기": 1, "후": 3, "간편해서": 1, "뿌리기에는": 1, "삼백미리는": 1, "중간중간": 4, "고루고루분사됩니다": 1, "워낙에": 1, "방에": 1, "반신욕": 1, "스트레스": 1, "외출할": 3, "3스킨으로": 1, "열감이": 1, "작은사이즈는": 2, "애기들도": 1, "세란직후랑": 1, "계절타지않고": 1, "사계절내내": 1, "막뿌리기에": 1, "뜨거운": 1, "보일러": 1, "대용량이라": 1, "꾹": 1, "나와서": 3, "간지럽거나": 1, "이용하기": 1, "응급용으로": 1, "요거로": 1, "예민해진": 1, "순간적인": 1, "쓱하고": 1, "진정시키는": 1, "생각없이": 2, "안개분사로되어있어서": 1, "피부타입없이": 1, "회사에두고쓰는": 1, "달바미스트랑": 1, "틈날": 1, "데일리템이에용": 1, "처음": 1, "건조할때도": 1, "햇빛뜨거운날": 1, "애용하는": 1, "빨개져": 1, "상관없이": 3, "후에도": 1, "뿌릴때": 2, "휴대용이필요해서": 1, "가끔씩": 1, "언제써도": 1, "하루에": 2, "끝까지": 1, "집중되지": 1, "않고": 1, "자그없이": 1, "얼굴에서": 1, "얼굴말고도": 1, "샀어요스킨": 1, "두고두고": 1, "그런용도로": 1, "기내용으로": 1, "하며": 1, "누르는": 1, "중앙에": 1, "여행용으로도": 1, "스킨토너": 1, "레이어링화장솜": 1, "귀찮을땐": 1, "더운": 3, "여름날씨": 1, "모든계절에": 1, "분사력은정말좋아요": 1, "목까지": 1, "비행할때": 1, "일하는": 1, "세인": 1, "흔들어": 1, "여러": 1, "보통": 1, "따로": 1, "분사력도좋구요": 1, "데일리템으로": 2, "미니미스트는": 1, "스킨대룡으로도": 1, "차갑게": 1, "하나두고": 1, "화장때문에": 1, "봄에": 1, "가지고다니기": 1, "집중적으로": 1, "기본적인": 1, "집에서나": 2, "세수하듯이": 1, "어느때에도": 1, "물갈이": 1, "어느피부타입이든": 1, "야외활동으로": 1, "화장실가서": 1, "잡은": 1, "화장지운": 1, "화장한": 1, "외출할때도": 1, "쿠션": 1, "퐁퐁": 1, "피부타입상관없이": 1, "어디하나": 1, "없이": 1, "미스트용으로": 1, "땀": 1, "미스트팩할때": 1, "휴대가": 1, "골": 1, "양많아서": 1, "더울": 2, "타입": 1, "가리지": 2, "흡수도": 1, "만만하게": 1, "닥토용으로": 1, "막뿌리기도": 1, "용으로는": 1, "남녀노소": 2, "진정팩으로": 1, "여자남자": 1, "좋아요": 4, "화장전에도": 1, "피부과에서도": 1, "화장실에도": 1, "맨날": 3, "요즘은": 1, "넓고": 1, "해외여행갈때나": 1, "스킨하기전에": 1, "메이크업할때나": 1, "닦는": 1, "휴대하면서": 1, "피부상태에": 1, "침대": 3, "휴대용으로는": 2, "50": 2, "외출시나": 1, "바디용으로": 1, "원그리듯": 1, "번을": 1, "회사나": 1, "필요할때마다": 3, "뿌려놓고": 1, "간편한": 1, "휴대용": 1, "지하철은": 1, "스킨용으로": 1, "너무좋은": 1, "저도": 1, "강해요": 1, "즉각적인": 1, "전": 2, "매해": 1, "상처위에도": 1, "퍼프에도": 2, "수정화장할때": 1, "크기가": 1, "얼굴이든": 1, "집에서도": 1, "분사력인데": 1, "시원하게": 1, "안개분사와": 1, "어떤피부에나": 1, "기지고": 1, "수정화장할때도": 1, "분사하는게": 1, "휴대하기엔": 1, "씻고나오면": 1, "활용도도": 1, "크기도": 1, "샤워랑": 1, "세수랑": 1, "팩": 3, "마른": 1, "보습하고": 1, "데일리로쓰기": 1, "되어서": 1, "건조함에": 1, "병원에서도": 1, "맨날맨날": 1, "지친": 1, "사계절용으로": 1, "머리부터": 1, "아기한테도": 1, "있으니": 1, "집밖에": 1, "다닐때": 1, "휴대하기네도": 1, "제품을": 1, "나온": 1, "아침": 4, "학교에가지고": 1, "휴대시": 1, "소분해서": 1, "건조하지않게": 1, "밤이든": 1, "되는": 1, "휴대할게": 1, "직후에": 1, "작은통": 1, "욕실이랑": 1, "스킨대신에": 1, "옆에": 1, "사물함에": 1, "데일리용으로": 1, "안개분사는좋은데": 1, "기내반입이": 1, "화장하거나": 1, "안개분사라는": 1, "헬스장에도": 1, "한병씩가지고있으면": 1, "저녁": 1, "잇습니다": 1, "쿠션할때": 1, "미스트로도": 1, "방마다": 1, "헤어스타일링": 1, "어디서든": 1, "건조해지기": 1, "팔다리에도": 1, "회사집": 1, "안개분사느낌으로": 1, "쓸수있는": 1, "분사형식": 1, "분사할때도": 1, "사진에": 1, "일과중": 1, "페이스": 1, "개별포장": 1, "이거맨날씀": 1, "휴대하기에는": 2, "누규나": 1, "일할때": 1, "아이가": 1, "아이들고": 1, "요걸": 1, "아이들이": 1, "최고인거같아요": 1, "가끔은": 2, "4계절에": 1, "휴대편리": 1, "용량별로": 1, "분사력굉장하고": 1, "마르면": 1, "여름만": 1, "이것도": 1, "친오빠랑": 1, "수분만": 1, "분사되어서": 1, "여름철엔": 1, "분사되니": 1, "무더위에": 1, "수정화장하기": 1, "전후로": 1, "난": 1, "부위에": 2, "예민한": 1, "화장실에서": 1, "스킨바르기전에도": 1, "좋습니다": 1, "화장실에놔두고": 1, "세수끝나고": 1, "화장이": 2, "뿌려져서": 1, "붉어지고": 1, "휴대성": 2, "여행시에도": 1, "좋다고": 2, "대신": 3, "휘뚜루": 1, "안개분사되는": 1, "토너바르기": 1, "일할": 1, "딱인듯": 1, "언제어디서나": 1, "뿌려주면": 1, "쓰기에": 2, "뿌려주기에는": 1, "일과": 1, "뿌려도": 1, "타입이라": 1, "투명해져서": 1, "여행시": 1, "사용하실": 1, "해야": 1, "안개미사에": 1, "주말에도": 1, "이곳저곳에": 1, "분사력좋은편이에요": 1, "휴대": 1, "양팔에도": 1, "얘로만": 1, "뜨겁거나": 1, "막뿌리기좋아요": 1, "파우치에": 1, "미스트팩으로": 1, "무난하고": 2, "가스분사형이라서": 1, "토너패드나": 1, "좋지만": 1, "분사나": 1, "저녁엔": 1, "집이랑": 1, "꾸준히": 1, "좋더라고요": 1, "가스충전식이라": 1, "300는": 1, "화장솜으로": 1, "귀여운": 1, "께끼까지": 1, "쉬는시간": 1, "몸에뿌려도": 1, "가장쓰기": 1, "막쓰기도": 1, "지금쓰기좋아요": 1, "목적으로만": 1, "분사감도": 1, "피부타입이나": 1, "안개미스트식이라": 1, "양조절하기도": 1, "남녀": 1, "노소": 1, "남녀누가": 1, "편하게쓰는편이에요": 1, "사무실같이": 1, "안개분": 1, "사이즈별로": 1, "열오를때나": 1, "사무실이": 1, "여행강때": 1, "기내안에도": 1, "활용도가": 1, "거즈에": 1, "듬뿍듬뿍": 1, "좋은거같아오": 1, "최고입니다": 1, "사실미스트로": 1, "나왔을": 1, "자주에서": 1, "기내에서도": 1, "500는": 1, "150": 1, "세수하면": 1, "어유": 1, "닦토로": 1, "가방이든": 1, "얹어져서": 1, "휴대용으로가지고다니려고": 1, "휴대하고다니면서": 1, "얼굴바디": 1, "나오기": 1, "바쁜": 1, "휴가나": 1, "외출": 1, "여드름피부나": 1, "스킨팩에도": 1, "토너대신": 1, "스킨대용": 1, "결정리": 1, "으로도": 1, "드라이하게": 1, "3인가족이": 1, "다같이": 1, "일정하게": 1, "수분소실": 1, "막는": 1, "일하면서": 1, "여름보다는": 1, "아니더라고": 1, "수분크림": 1, "받았을": 1, "손으로": 1, "3시간에": 1, "다른제품": 1}